mp4sp/__init__.py
mp4sp/cli.py
mp4sp-1.0.3.dist-info/METADATA
mp4sp-1.0.3.dist-info/WHEEL
mp4sp-1.0.3.dist-info/entry_points.txt
mp4sp-1.0.3.dist-info/licenses/LICENSE
mp4sp-1.0.3.dist-info/RECORD
