Metadata-Version: 2.4
Name: mp4sp
Version: 1.0.3
Summary: Split MP4 files into multiple clips from a CSV segment list.
Author: Katsuya Hyodo
License: MIT License
License-File: LICENSE
Keywords: cli,ffmpeg,mp4,split,video
Classifier: License :: OSI Approved :: MIT License
Classifier: Operating System :: OS Independent
Classifier: Programming Language :: Python :: 3
Classifier: Programming Language :: Python :: 3.10
Classifier: Programming Language :: Python :: 3.11
Classifier: Programming Language :: Python :: 3.12
Requires-Python: >=3.10.12
Requires-Dist: ffmpeg==1.4
